murkrow/__init__.py
murkrow-0.14.0.dist-info/METADATA
murkrow-0.14.0.dist-info/WHEEL
murkrow-0.14.0.dist-info/top_level.txt
murkrow-0.14.0.dist-info/RECORD
